aws_mfa-0.0.12.data/scripts/aws-mfa
aws_mfa-0.0.12.dist-info/DESCRIPTION.rst
aws_mfa-0.0.12.dist-info/METADATA
aws_mfa-0.0.12.dist-info/RECORD
aws_mfa-0.0.12.dist-info/WHEEL
aws_mfa-0.0.12.dist-info/entry_points.txt
aws_mfa-0.0.12.dist-info/metadata.json
aws_mfa-0.0.12.dist-info/top_level.txt
awsmfa/__init__.py
awsmfa/config.py
awsmfa/util.py
