Metadata-Version: 2.0
Name: aws-mfa
Version: 0.0.12
Summary: Manage AWS MFA Security Credentials
Home-page: https://github.com/broamski/aws-mfa
Author: Brian Nuszkowski
Author-email: brian@bnuz.co
License: MIT
Platform: UNKNOWN
Requires-Dist: boto3
